README.md
setup.py
sw_excel_parser/__init__.py
sw_excel_parser/engines.py
sw_excel_parser/fields.py
sw_excel_parser/items.py
sw_excel_parser/parsers.py
sw_excel_parser/validators.py
sw_excel_parser.egg-info/PKG-INFO
sw_excel_parser.egg-info/SOURCES.txt
sw_excel_parser.egg-info/dependency_links.txt
sw_excel_parser.egg-info/requires.txt
sw_excel_parser.egg-info/top_level.txt