Metadata-Version: 1.0
Name: sw-excel-parser
Version: 0.0.6
Summary: Soft Way Microsoft Excel documents parsing package
Home-page: https://github.com/telminov/sw-excel-parser
Author: Telminov Sergey
Author-email: sergey@telminov.ru
License: MIT
Platform: UNKNOWN
